langchain_zt/__init__.py
langchain_zt/api_agent.py
langchain_zt/zero_trusted_ai_llm.py
langchain_zt-0.0.1.dist-info/METADATA
langchain_zt-0.0.1.dist-info/WHEEL
langchain_zt-0.0.1.dist-info/top_level.txt
langchain_zt-0.0.1.dist-info/RECORD
